{
  "Afghanistan": { "country_ne":"Afghanistan", "pop_est":34124811, "gdp_est":64080, "economy":"7. Least developed region", "income_group":"5. Low income", "continent":"Asia", "region":"Asia"},
  "Albania": { "country_ne":"Albania", "pop_est":3047987, "gdp_est":33900, "economy":"6. Developing region", "income_group":"4. Lower middle income", "continent":"Europe", "region":"Europe"},
  "Algeria": { "country_ne":"Algeria", "pop_est":40969443, "gdp_est":609400, "economy":"6. Developing region", "income_group":"3. Upper middle income", "continent":"Africa", "region":"Africa"},
  "Andorra": { "country_ne":"Andorra", "pop_est":85702, "gdp_est":3327, "economy":"2. Developed region: nonG7", "income_group":"2. High income: nonOECD", "continent":"Europe", "region":"Europe"},
  "Angola": { "country_ne":"Angola", "pop_est":29310273, "gdp_est":189000, "economy":"7. Least developed region", "income_group":"3. Upper middle income", "continent":"Africa", "region":"Africa"},
  "Anguilla": { "country_ne":"Anguilla", "pop_est":17087, "gdp_est":175.4, "economy":"6. Developing region", "income_group":"3. Upper middle income", "continent":"North America", "region":"Americas"},
  "Antigua and Barbuda": { "country_ne":"Antigua and Barbuda", "pop_est":94731, "gdp_est":2171, "economy":"6. Developing region", "income_group":"3. Upper middle income", "continent":"North America", "region":"Americas"},
  "Argentina": { "country_ne":"Argentina", "pop_est":44293293, "gdp_est":879400, "economy":"5. Emerging region: G20", "income_group":"3. Upper middle income", "continent":"South America", "region":"Americas"},
  "Armenia": { "country_ne":"Armenia", "pop_est":3045191, "gdp_est":26300, "economy":"6. Developing region", "income_group":"4. Lower middle income", "continent":"Asia", "region":"Asia"},
  "Aruba": { "country_ne":"Aruba", "pop_est":115120, "gdp_est":2516, "economy":"6. Developing region", "income_group":"2. High income: nonOECD", "continent":"North America", "region":"Americas"},
  "Australia": { "country_ne":"Australia", "pop_est":23232413, "gdp_est":1189000, "economy":"2. Developed region: nonG7", "income_group":"1. High income: OECD", "continent":"Oceania", "region":"Oceania"},
  "Austria": { "country_ne":"Austria", "pop_est":8754413, "gdp_est":416600, "economy":"2. Developed region: nonG7", "income_group":"1. High income: OECD", "continent":"Europe", "region":"Europe"},
  "Azerbaijan": { "country_ne":"Azerbaijan", "pop_est":9961396, "gdp_est":167900, "economy":"6. Developing region", "income_group":"3. Upper middle income", "continent":"Asia", "region":"Asia"},
  "Bahamas": { "country_ne":"Bahamas", "pop_est":329988, "gdp_est":9066, "economy":"6. Developing region", "income_group":"2. High income: nonOECD", "continent":"North America", "region":"Americas"},
  "Bahrain": { "country_ne":"Bahrain", "pop_est":1410942, "gdp_est":66370, "economy":"6. Developing region", "income_group":"2. High income: nonOECD", "continent":"Asia", "region":"Asia"},
  "Bangladesh": { "country_ne":"Bangladesh", "pop_est":157826578, "gdp_est":628400, "economy":"7. Least developed region", "income_group":"5. Low income", "continent":"Asia", "region":"Asia"},
  "Barbados": { "country_ne":"Barbados", "pop_est":292336, "gdp_est":4804, "economy":"6. Developing region", "income_group":"2. High income: nonOECD", "continent":"North America", "region":"Americas"},
  "Belarus": { "country_ne":"Belarus", "pop_est":9549747, "gdp_est":165400, "economy":"6. Developing region", "income_group":"3. Upper middle income", "continent":"Europe", "region":"Europe"},
  "Belgium": { "country_ne":"Belgium", "pop_est":11491346, "gdp_est":508600, "economy":"2. Developed region: nonG7", "income_group":"1. High income: OECD", "continent":"Europe", "region":"Europe"},
  "Belize": { "country_ne":"Belize", "pop_est":360346, "gdp_est":3088, "economy":"6. Developing region", "income_group":"4. Lower middle income", "continent":"North America", "region":"Americas"},
  "Benin": { "country_ne":"Benin", "pop_est":11038805, "gdp_est":24310, "economy":"7. Least developed region", "income_group":"5. Low income", "continent":"Africa", "region":"Africa"},
  "Bermuda": { "country_ne":"Bermuda", "pop_est":70864, "gdp_est":5198, "economy":"2. Developed region: nonG7", "income_group":"2. High income: nonOECD", "continent":"North America", "region":"Americas"},
  "Bhutan": { "country_ne":"Bhutan", "pop_est":758288, "gdp_est":6432, "economy":"7. Least developed region", "income_group":"4. Lower middle income", "continent":"Asia", "region":"Asia"},
  "Bolivia": { "country_ne":"Bolivia", "pop_est":11138234, "gdp_est":78350, "economy":"5. Emerging region: G20", "income_group":"4. Lower middle income", "continent":"South America", "region":"Americas"},
  "Bonaire Sint Eustatius and Saba": { "country_ne":"", "pop_est":0, "gdp_est":0, "economy":"", "income_group":"", "continent":"", "region":""},
  "Bosnia and Herzegovina": { "country_ne":"Bosnia and Herzegovina", "pop_est":3856181, "gdp_est":42530, "economy":"6. Developing region", "income_group":"3. Upper middle income", "continent":"Europe", "region":"Europe"},
  "Botswana": { "country_ne":"Botswana", "pop_est":2214858, "gdp_est":35900, "economy":"6. Developing region", "income_group":"3. Upper middle income", "continent":"Africa", "region":"Africa"},
  "Brazil": { "country_ne":"Brazil", "pop_est":207353391, "gdp_est":3081000, "economy":"3. Emerging region: BRIC", "income_group":"3. Upper middle income", "continent":"South America", "region":"Americas"},
  "British Virgin Islands": { "country_ne":"British Virgin Islands", "pop_est":35015, "gdp_est":500, "economy":"2. Developed region: nonG7", "income_group":"1. High income: OECD", "continent":"North America", "region":"Americas"},
  "Brunei": { "country_ne":"Brunei", "pop_est":443593, "gdp_est":33730, "economy":"6. Developing region", "income_group":"2. High income: nonOECD", "continent":"Asia", "region":"Asia"},
  "Bulgaria": { "country_ne":"Bulgaria", "pop_est":7101510, "gdp_est":143100, "economy":"2. Developed region: nonG7", "income_group":"3. Upper middle income", "continent":"Europe", "region":"Europe"},
  "Burkina Faso": { "country_ne":"Burkina Faso", "pop_est":20107509, "gdp_est":32990, "economy":"7. Least developed region", "income_group":"5. Low income", "continent":"Africa", "region":"Africa"},
  "Burundi": { "country_ne":"Burundi", "pop_est":11466756, "gdp_est":7892, "economy":"7. Least developed region", "income_group":"5. Low income", "continent":"Africa", "region":"Africa"},
  "Cambodia": { "country_ne":"Cambodia", "pop_est":16204486, "gdp_est":58940, "economy":"7. Least developed region", "income_group":"5. Low income", "continent":"Asia", "region":"Asia"},
  "Cameroon": { "country_ne":"Cameroon", "pop_est":24994885, "gdp_est":77240, "economy":"6. Developing region", "income_group":"4. Lower middle income", "continent":"Africa", "region":"Africa"},
  "Canada": { "country_ne":"Canada", "pop_est":35623680, "gdp_est":1674000, "economy":"1. Developed region: G7", "income_group":"1. High income: OECD", "continent":"North America", "region":"Americas"},
  "Cape Verde": { "country_ne":"Cabo Verde", "pop_est":560899, "gdp_est":3583, "economy":"6. Developing region", "income_group":"4. Lower middle income", "continent":"Africa", "region":"Africa"},
  "Cayman Islands": { "country_ne":"Cayman Islands", "pop_est":58441, "gdp_est":2507, "economy":"5. Emerging region: G20", "income_group":"2. High income: nonOECD", "continent":"North America", "region":"Americas"},
  "Central African Republic": { "country_ne":"Central African Republic", "pop_est":5625118, "gdp_est":3206, "economy":"7. Least developed region", "income_group":"5. Low income", "continent":"Africa", "region":"Africa"},
  "Chad": { "country_ne":"Chad", "pop_est":12075985, "gdp_est":30590, "economy":"7. Least developed region", "income_group":"5. Low income", "continent":"Africa", "region":"Africa"},
  "Chile": { "country_ne":"Chile", "pop_est":17789267, "gdp_est":436100, "economy":"5. Emerging region: G20", "income_group":"3. Upper middle income", "continent":"South America", "region":"Americas"},
  "China": { "country_ne":"China", "pop_est":1379302771, "gdp_est":21140000, "economy":"3. Emerging region: BRIC", "income_group":"3. Upper middle income", "continent":"Asia", "region":"Asia"},
  "Colombia": { "country_ne":"Colombia", "pop_est":47698524, "gdp_est":688000, "economy":"6. Developing region", "income_group":"3. Upper middle income", "continent":"South America", "region":"Americas"},
  "Comoros": { "country_ne":"Comoros", "pop_est":808080, "gdp_est":1259, "economy":"7. Least developed region", "income_group":"5. Low income", "continent":"Africa", "region":"Africa"},
  "Congo": { "country_ne":"Republic of the Congo", "pop_est":4954674, "gdp_est":30270, "economy":"6. Developing region", "income_group":"4. Lower middle income", "continent":"Africa", "region":"Africa"},
  "Costa Rica": { "country_ne":"Costa Rica", "pop_est":4930258, "gdp_est":79260, "economy":"5. Emerging region: G20", "income_group":"3. Upper middle income", "continent":"North America", "region":"Americas"},
  "Cote d'Ivoire": { "country_ne":"Ivory Coast", "pop_est":24184810, "gdp_est":87120, "economy":"6. Developing region", "income_group":"4. Lower middle income", "continent":"Africa", "region":"Africa"},
  "Croatia": { "country_ne":"Croatia", "pop_est":4292095, "gdp_est":94240, "economy":"2. Developed region: nonG7", "income_group":"2. High income: nonOECD", "continent":"Europe", "region":"Europe"},
  "Cuba": { "country_ne":"Cuba", "pop_est":11147407, "gdp_est":132900, "economy":"5. Emerging region: G20", "income_group":"3. Upper middle income", "continent":"North America", "region":"Americas"},
  "Curacao": { "country_ne":"Curacao", "pop_est":149648, "gdp_est":3128, "economy":"6. Developing region", "income_group":"2. High income: nonOECD", "continent":"North America", "region":"Americas"},
  "Cyprus": { "country_ne":"Cyprus", "pop_est":1221549, "gdp_est":29260, "economy":"6. Developing region", "income_group":"2. High income: nonOECD", "continent":"Asia", "region":"Asia"},
  "Czech Republic": { "country_ne":"Czechia", "pop_est":10674723, "gdp_est":350900, "economy":"2. Developed region: nonG7", "income_group":"1. High income: OECD", "continent":"Europe", "region":"Europe"},
  "Democratic Republic of Congo": { "country_ne":"Democratic Republic of the Congo", "pop_est":83301151, "gdp_est":66010, "economy":"7. Least developed region", "income_group":"5. Low income", "continent":"Africa", "region":"Africa"},
  "Denmark": { "country_ne":"Denmark", "pop_est":5605948, "gdp_est":264800, "economy":"2. Developed region: nonG7", "income_group":"1. High income: OECD", "continent":"Europe", "region":"Europe"},
  "Djibouti": { "country_ne":"Djibouti", "pop_est":865267, "gdp_est":3345, "economy":"7. Least developed region", "income_group":"4. Lower middle income", "continent":"Africa", "region":"Africa"},
  "Dominica": { "country_ne":"Dominica", "pop_est":73897, "gdp_est":812, "economy":"6. Developing region", "income_group":"3. Upper middle income", "continent":"North America", "region":"Americas"},
  "Dominican Republic": { "country_ne":"Dominican Republic", "pop_est":10734247, "gdp_est":161900, "economy":"6. Developing region", "income_group":"3. Upper middle income", "continent":"North America", "region":"Americas"},
  "Ecuador": { "country_ne":"Ecuador", "pop_est":16290913, "gdp_est":182400, "economy":"6. Developing region", "income_group":"3. Upper middle income", "continent":"South America", "region":"Americas"},
  "Egypt": { "country_ne":"Egypt", "pop_est":97041072, "gdp_est":1105000, "economy":"5. Emerging region: G20", "income_group":"4. Lower middle income", "continent":"Africa", "region":"Africa"},
  "El Salvador": { "country_ne":"El Salvador", "pop_est":6172011, "gdp_est":54790, "economy":"6. Developing region", "income_group":"4. Lower middle income", "continent":"North America", "region":"Americas"},
  "Equatorial Guinea": { "country_ne":"Equatorial Guinea", "pop_est":778358, "gdp_est":31770, "economy":"7. Least developed region", "income_group":"2. High income: nonOECD", "continent":"Africa", "region":"Africa"},
  "Eritrea": { "country_ne":"Eritrea", "pop_est":5918919, "gdp_est":9169, "economy":"7. Least developed region", "income_group":"5. Low income", "continent":"Africa", "region":"Africa"},
  "Estonia": { "country_ne":"Estonia", "pop_est":1251581, "gdp_est":38700, "economy":"2. Developed region: nonG7", "income_group":"1. High income: OECD", "continent":"Europe", "region":"Europe"},
  "Ethiopia": { "country_ne":"Ethiopia", "pop_est":105350020, "gdp_est":174700, "economy":"7. Least developed region", "income_group":"5. Low income", "continent":"Africa", "region":"Africa"},
  "Faeroe Islands": { "country_ne":"Faroe Islands", "pop_est":50730, "gdp_est":2001, "economy":"2. Developed region: nonG7", "income_group":"2. High income: nonOECD", "continent":"Europe", "region":"Europe"},
  "Falkland Islands": { "country_ne":"Falkland Islands", "pop_est":2931, "gdp_est":281.8, "economy":"2. Developed region: nonG7", "income_group":"1. High income: OECD", "continent":"South America", "region":"Americas"},
  "Fiji": { "country_ne":"Fiji", "pop_est":920938, "gdp_est":8374, "economy":"6. Developing region", "income_group":"4. Lower middle income", "continent":"Oceania", "region":"Oceania"},
  "Finland": { "country_ne":"Finland", "pop_est":5491218, "gdp_est":224137, "economy":"2. Developed region: nonG7", "income_group":"1. High income: OECD", "continent":"Europe", "region":"Europe"},
  "France": { "country_ne":"France", "pop_est":67106161, "gdp_est":2699000, "economy":"1. Developed region: G7", "income_group":"1. High income: OECD", "continent":"Europe", "region":"Europe"},
  "French Polynesia": { "country_ne":"French Polynesia", "pop_est":287881, "gdp_est":5490, "economy":"6. Developing region", "income_group":"2. High income: nonOECD", "continent":"Oceania", "region":"Oceania"},
  "Gabon": { "country_ne":"Gabon", "pop_est":1772255, "gdp_est":35980, "economy":"6. Developing region", "income_group":"3. Upper middle income", "continent":"Africa", "region":"Africa"},
  "Gambia": { "country_ne":"Gambia", "pop_est":2051363, "gdp_est":3387, "economy":"7. Least developed region", "income_group":"5. Low income", "continent":"Africa", "region":"Africa"},
  "Georgia": { "country_ne":"Georgia", "pop_est":4926330, "gdp_est":37270, "economy":"6. Developing region", "income_group":"4. Lower middle income", "continent":"Asia", "region":"Asia"},
  "Germany": { "country_ne":"Germany", "pop_est":80594017, "gdp_est":3979000, "economy":"1. Developed region: G7", "income_group":"1. High income: OECD", "continent":"Europe", "region":"Europe"},
  "Ghana": { "country_ne":"Ghana", "pop_est":27499924, "gdp_est":120800, "economy":"6. Developing region", "income_group":"4. Lower middle income", "continent":"Africa", "region":"Africa"},
  "Gibraltar": { "country_ne":"", "pop_est":0, "gdp_est":0, "economy":"", "income_group":"", "continent":"", "region":""},
  "Greece": { "country_ne":"Greece", "pop_est":10768477, "gdp_est":290500, "economy":"2. Developed region: nonG7", "income_group":"1. High income: OECD", "continent":"Europe", "region":"Europe"},
  "Greenland": { "country_ne":"Greenland", "pop_est":57713, "gdp_est":2173, "economy":"2. Developed region: nonG7", "income_group":"2. High income: nonOECD", "continent":"North America", "region":"Americas"},
  "Grenada": { "country_ne":"Grenada", "pop_est":111724, "gdp_est":1511, "economy":"6. Developing region", "income_group":"3. Upper middle income", "continent":"North America", "region":"Americas"},
  "Guam": { "country_ne":"Guam", "pop_est":167358, "gdp_est":4882, "economy":"6. Developing region", "income_group":"2. High income: nonOECD", "continent":"Oceania", "region":"Oceania"},
  "Guatemala": { "country_ne":"Guatemala", "pop_est":15460732, "gdp_est":131800, "economy":"6. Developing region", "income_group":"4. Lower middle income", "continent":"North America", "region":"Americas"},
  "Guernsey": { "country_ne":"Guernsey", "pop_est":66502, "gdp_est":3465, "economy":"2. Developed region: nonG7", "income_group":"2. High income: nonOECD", "continent":"Europe", "region":"Europe"},
  "Guinea": { "country_ne":"Guinea", "pop_est":12413867, "gdp_est":16080, "economy":"7. Least developed region", "income_group":"5. Low income", "continent":"Africa", "region":"Africa"},
  "Guinea-Bissau": { "country_ne":"Guinea-Bissau", "pop_est":1792338, "gdp_est":2851, "economy":"7. Least developed region", "income_group":"5. Low income", "continent":"Africa", "region":"Africa"},
  "Guyana": { "country_ne":"Guyana", "pop_est":737718, "gdp_est":6093, "economy":"6. Developing region", "income_group":"4. Lower middle income", "continent":"South America", "region":"Americas"},
  "Haiti": { "country_ne":"Haiti", "pop_est":10646714, "gdp_est":19340, "economy":"7. Least developed region", "income_group":"5. Low income", "continent":"North America", "region":"Americas"},
  "Honduras": { "country_ne":"Honduras", "pop_est":9038741, "gdp_est":43190, "economy":"6. Developing region", "income_group":"4. Lower middle income", "continent":"North America", "region":"Americas"},
  "Hungary": { "country_ne":"Hungary", "pop_est":9850845, "gdp_est":267600, "economy":"2. Developed region: nonG7", "income_group":"1. High income: OECD", "continent":"Europe", "region":"Europe"},
  "Iceland": { "country_ne":"Iceland", "pop_est":339747, "gdp_est":16150, "economy":"2. Developed region: nonG7", "income_group":"1. High income: OECD", "continent":"Europe", "region":"Europe"},
  "India": { "country_ne":"India", "pop_est":1281935911, "gdp_est":8721000, "economy":"3. Emerging region: BRIC", "income_group":"4. Lower middle income", "continent":"Asia", "region":"Asia"},
  "Indonesia": { "country_ne":"Indonesia", "pop_est":260580739, "gdp_est":3028000, "economy":"4. Emerging region: MIKT", "income_group":"4. Lower middle income", "continent":"Asia", "region":"Asia"},
  "International": { "country_ne":"", "pop_est":0, "gdp_est":0, "economy":"", "income_group":"", "continent":"", "region":""},
  "Iran": { "country_ne":"Iran", "pop_est":82021564, "gdp_est":1459000, "economy":"5. Emerging region: G20", "income_group":"3. Upper middle income", "continent":"Asia", "region":"Asia"},
  "Iraq": { "country_ne":"Iraq", "pop_est":39192111, "gdp_est":596700, "economy":"6. Developing region", "income_group":"4. Lower middle income", "continent":"Asia", "region":"Asia"},
  "Ireland": { "country_ne":"Ireland", "pop_est":5011102, "gdp_est":322000, "economy":"2. Developed region: nonG7", "income_group":"1. High income: OECD", "continent":"Europe", "region":"Europe"},
  "Isle of Man": { "country_ne":"Isle of Man", "pop_est":88815, "gdp_est":7428, "economy":"2. Developed region: nonG7", "income_group":"2. High income: nonOECD", "continent":"Europe", "region":"Europe"},
  "Israel": { "country_ne":"Israel", "pop_est":8299706, "gdp_est":297000, "economy":"2. Developed region: nonG7", "income_group":"1. High income: OECD", "continent":"Asia", "region":"Asia"},
  "Italy": { "country_ne":"Italy", "pop_est":62137802, "gdp_est":2221000, "economy":"1. Developed region: G7", "income_group":"1. High income: OECD", "continent":"Europe", "region":"Europe"},
  "Jamaica": { "country_ne":"Jamaica", "pop_est":2990561, "gdp_est":25390, "economy":"6. Developing region", "income_group":"3. Upper middle income", "continent":"North America", "region":"Americas"},
  "Japan": { "country_ne":"Japan", "pop_est":126451398, "gdp_est":4932000, "economy":"1. Developed region: G7", "income_group":"1. High income: OECD", "continent":"Asia", "region":"Asia"},
  "Jersey": { "country_ne":"Jersey", "pop_est":98840, "gdp_est":5080, "economy":"2. Developed region: nonG7", "income_group":"2. High income: nonOECD", "continent":"Europe", "region":"Europe"},
  "Jordan": { "country_ne":"Jordan", "pop_est":10248069, "gdp_est":86190, "economy":"6. Developing region", "income_group":"3. Upper middle income", "continent":"Asia", "region":"Asia"},
  "Kazakhstan": { "country_ne":"Kazakhstan", "pop_est":18556698, "gdp_est":460700, "economy":"6. Developing region", "income_group":"3. Upper middle income", "continent":"Asia", "region":"Asia"},
  "Kenya": { "country_ne":"Kenya", "pop_est":47615739, "gdp_est":152700, "economy":"5. Emerging region: G20", "income_group":"5. Low income", "continent":"Africa", "region":"Africa"},
  "Kosovo": { "country_ne":"Kosovo", "pop_est":1895250, "gdp_est":18490, "economy":"6. Developing region", "income_group":"4. Lower middle income", "continent":"Europe", "region":"Europe"},
  "Kuwait": { "country_ne":"Kuwait", "pop_est":2875422, "gdp_est":301100, "economy":"6. Developing region", "income_group":"2. High income: nonOECD", "continent":"Asia", "region":"Asia"},
  "Kyrgyzstan": { "country_ne":"Kyrgyzstan", "pop_est":5789122, "gdp_est":21010, "economy":"6. Developing region", "income_group":"5. Low income", "continent":"Asia", "region":"Asia"},
  "Laos": { "country_ne":"Laos", "pop_est":7126706, "gdp_est":40960, "economy":"7. Least developed region", "income_group":"4. Lower middle income", "continent":"Asia", "region":"Asia"},
  "Latvia": { "country_ne":"Latvia", "pop_est":1944643, "gdp_est":50650, "economy":"2. Developed region: nonG7", "income_group":"3. Upper middle income", "continent":"Europe", "region":"Europe"},
  "Lebanon": { "country_ne":"Lebanon", "pop_est":6229794, "gdp_est":85160, "economy":"6. Developing region", "income_group":"3. Upper middle income", "continent":"Asia", "region":"Asia"},
  "Lesotho": { "country_ne":"Lesotho", "pop_est":1958042, "gdp_est":6019, "economy":"7. Least developed region", "income_group":"4. Lower middle income", "continent":"Africa", "region":"Africa"},
  "Liberia": { "country_ne":"Liberia", "pop_est":4689021, "gdp_est":3881, "economy":"7. Least developed region", "income_group":"5. Low income", "continent":"Africa", "region":"Africa"},
  "Libya": { "country_ne":"Libya", "pop_est":6653210, "gdp_est":90890, "economy":"6. Developing region", "income_group":"3. Upper middle income", "continent":"Africa", "region":"Africa"},
  "Liechtenstein": { "country_ne":"Liechtenstein", "pop_est":38244, "gdp_est":4978, "economy":"2. Developed region: nonG7", "income_group":"2. High income: nonOECD", "continent":"Europe", "region":"Europe"},
  "Lithuania": { "country_ne":"Lithuania", "pop_est":2823859, "gdp_est":85620, "economy":"2. Developed region: nonG7", "income_group":"3. Upper middle income", "continent":"Europe", "region":"Europe"},
  "Luxembourg": { "country_ne":"Luxembourg", "pop_est":594130, "gdp_est":58740, "economy":"2. Developed region: nonG7", "income_group":"1. High income: OECD", "continent":"Europe", "region":"Europe"},
  "Macedonia": { "country_ne":"Macedonia", "pop_est":2103721, "gdp_est":29520, "economy":"6. Developing region", "income_group":"3. Upper middle income", "continent":"Europe", "region":"Europe"},
  "Madagascar": { "country_ne":"Madagascar", "pop_est":25054161, "gdp_est":36860, "economy":"7. Least developed region", "income_group":"5. Low income", "continent":"Africa", "region":"Africa"},
  "Malawi": { "country_ne":"Malawi", "pop_est":19196246, "gdp_est":21200, "economy":"7. Least developed region", "income_group":"5. Low income", "continent":"Africa", "region":"Africa"},
  "Malaysia": { "country_ne":"Malaysia", "pop_est":31381992, "gdp_est":863000, "economy":"6. Developing region", "income_group":"3. Upper middle income", "continent":"Asia", "region":"Asia"},
  "Maldives": { "country_ne":"Maldives", "pop_est":392709, "gdp_est":5407, "economy":"6. Developing region", "income_group":"3. Upper middle income", "continent":"Asia", "region":"Asia"},
  "Mali": { "country_ne":"Mali", "pop_est":17885245, "gdp_est":38090, "economy":"7. Least developed region", "income_group":"5. Low income", "continent":"Africa", "region":"Africa"},
  "Malta": { "country_ne":"Malta", "pop_est":416338, "gdp_est":16320, "economy":"2. Developed region: nonG7", "income_group":"2. High income: nonOECD", "continent":"Europe", "region":"Europe"},
  "Mauritania": { "country_ne":"Mauritania", "pop_est":3758571, "gdp_est":16710, "economy":"7. Least developed region", "income_group":"5. Low income", "continent":"Africa", "region":"Africa"},
  "Mauritius": { "country_ne":"Mauritius", "pop_est":1356388, "gdp_est":25850, "economy":"6. Developing region", "income_group":"3. Upper middle income", "continent":"Africa", "region":"Africa"},
  "Mexico": { "country_ne":"Mexico", "pop_est":124574795, "gdp_est":2307000, "economy":"4. Emerging region: MIKT", "income_group":"3. Upper middle income", "continent":"North America", "region":"Americas"},
  "Moldova": { "country_ne":"Moldova", "pop_est":3474121, "gdp_est":18540, "economy":"6. Developing region", "income_group":"4. Lower middle income", "continent":"Europe", "region":"Europe"},
  "Monaco": { "country_ne":"Monaco", "pop_est":30645, "gdp_est":7672, "economy":"2. Developed region: nonG7", "income_group":"2. High income: nonOECD", "continent":"Europe", "region":"Europe"},
  "Mongolia": { "country_ne":"Mongolia", "pop_est":3068243, "gdp_est":37000, "economy":"6. Developing region", "income_group":"4. Lower middle income", "continent":"Asia", "region":"Asia"},
  "Montenegro": { "country_ne":"Montenegro", "pop_est":642550, "gdp_est":10610, "economy":"6. Developing region", "income_group":"3. Upper middle income", "continent":"Europe", "region":"Europe"},
  "Montserrat": { "country_ne":"Montserrat", "pop_est":5292, "gdp_est":43.8, "economy":"6. Developing region", "income_group":"4. Lower middle income", "continent":"North America", "region":"Americas"},
  "Morocco": { "country_ne":"Morocco", "pop_est":33986655, "gdp_est":282800, "economy":"6. Developing region", "income_group":"4. Lower middle income", "continent":"Africa", "region":"Africa"},
  "Mozambique": { "country_ne":"Mozambique", "pop_est":26573706, "gdp_est":35010, "economy":"7. Least developed region", "income_group":"5. Low income", "continent":"Africa", "region":"Africa"},
  "Myanmar": { "country_ne":"Myanmar", "pop_est":55123814, "gdp_est":311100, "economy":"7. Least developed region", "income_group":"5. Low income", "continent":"Asia", "region":"Asia"},
  "Namibia": { "country_ne":"Namibia", "pop_est":2484780, "gdp_est":25990, "economy":"6. Developing region", "income_group":"3. Upper middle income", "continent":"Africa", "region":"Africa"},
  "Nepal": { "country_ne":"Nepal", "pop_est":29384297, "gdp_est":71520, "economy":"7. Least developed region", "income_group":"5. Low income", "continent":"Asia", "region":"Asia"},
  "Netherlands": { "country_ne":"Netherlands", "pop_est":17084719, "gdp_est":870800, "economy":"2. Developed region: nonG7", "income_group":"1. High income: OECD", "continent":"Europe", "region":"Europe"},
  "New Caledonia": { "country_ne":"New Caledonia", "pop_est":279070, "gdp_est":10770, "economy":"6. Developing region", "income_group":"2. High income: nonOECD", "continent":"Oceania", "region":"Oceania"},
  "New Zealand": { "country_ne":"New Zealand", "pop_est":4510327, "gdp_est":174800, "economy":"2. Developed region: nonG7", "income_group":"1. High income: OECD", "continent":"Oceania", "region":"Oceania"},
  "Nicaragua": { "country_ne":"Nicaragua", "pop_est":6025951, "gdp_est":33550, "economy":"6. Developing region", "income_group":"4. Lower middle income", "continent":"North America", "region":"Americas"},
  "Niger": { "country_ne":"Niger", "pop_est":19245344, "gdp_est":20150, "economy":"7. Least developed region", "income_group":"5. Low income", "continent":"Africa", "region":"Africa"},
  "Nigeria": { "country_ne":"Nigeria", "pop_est":190632261, "gdp_est":1089000, "economy":"5. Emerging region: G20", "income_group":"4. Lower middle income", "continent":"Africa", "region":"Africa"},
  "Northern Mariana Islands": { "country_ne":"Northern Mariana Islands", "pop_est":52263, "gdp_est":682, "economy":"6. Developing region", "income_group":"2. High income: nonOECD", "continent":"Oceania", "region":"Oceania"},
  "Norway": { "country_ne":"Norway", "pop_est":5320045, "gdp_est":364700, "economy":"2. Developed region: nonG7", "income_group":"1. High income: OECD", "continent":"Europe", "region":"Europe"},
  "Oman": { "country_ne":"Oman", "pop_est":3424386, "gdp_est":173100, "economy":"6. Developing region", "income_group":"2. High income: nonOECD", "continent":"Asia", "region":"Asia"},
  "Pakistan": { "country_ne":"Pakistan", "pop_est":204924861, "gdp_est":988200, "economy":"5. Emerging region: G20", "income_group":"4. Lower middle income", "continent":"Asia", "region":"Asia"},
  "Palestine": { "country_ne":"Palestine", "pop_est":4543126, "gdp_est":21220.77, "economy":"6. Developing region", "income_group":"4. Lower middle income", "continent":"Asia", "region":"Asia"},
  "Panama": { "country_ne":"Panama", "pop_est":3753142, "gdp_est":93120, "economy":"6. Developing region", "income_group":"3. Upper middle income", "continent":"North America", "region":"Americas"},
  "Papua New Guinea": { "country_ne":"Papua New Guinea", "pop_est":6909701, "gdp_est":28020, "economy":"6. Developing region", "income_group":"4. Lower middle income", "continent":"Oceania", "region":"Oceania"},
  "Paraguay": { "country_ne":"Paraguay", "pop_est":6943739, "gdp_est":64670, "economy":"5. Emerging region: G20", "income_group":"4. Lower middle income", "continent":"South America", "region":"Americas"},
  "Peru": { "country_ne":"Peru", "pop_est":31036656, "gdp_est":410400, "economy":"5. Emerging region: G20", "income_group":"3. Upper middle income", "continent":"South America", "region":"Americas"},
  "Philippines": { "country_ne":"Philippines", "pop_est":104256076, "gdp_est":801900, "economy":"5. Emerging region: G20", "income_group":"4. Lower middle income", "continent":"Asia", "region":"Asia"},
  "Poland": { "country_ne":"Poland", "pop_est":38476269, "gdp_est":1052000, "economy":"2. Developed region: nonG7", "income_group":"1. High income: OECD", "continent":"Europe", "region":"Europe"},
  "Portugal": { "country_ne":"Portugal", "pop_est":10839514, "gdp_est":297100, "economy":"2. Developed region: nonG7", "income_group":"1. High income: OECD", "continent":"Europe", "region":"Europe"},
  "Puerto Rico": { "country_ne":"Puerto Rico", "pop_est":3351827, "gdp_est":131000, "economy":"6. Developing region", "income_group":"2. High income: nonOECD", "continent":"North America", "region":"Americas"},
  "Qatar": { "country_ne":"Qatar", "pop_est":2314307, "gdp_est":334500, "economy":"6. Developing region", "income_group":"2. High income: nonOECD", "continent":"Asia", "region":"Asia"},
  "Romania": { "country_ne":"Romania", "pop_est":21529967, "gdp_est":441000, "economy":"2. Developed region: nonG7", "income_group":"3. Upper middle income", "continent":"Europe", "region":"Europe"},
  "Russia": { "country_ne":"Russia", "pop_est":142257519, "gdp_est":3745000, "economy":"3. Emerging region: BRIC", "income_group":"3. Upper middle income", "continent":"Europe", "region":"Europe"},
  "Rwanda": { "country_ne":"Rwanda", "pop_est":11901484, "gdp_est":21970, "economy":"7. Least developed region", "income_group":"5. Low income", "continent":"Africa", "region":"Africa"},
  "Saint Kitts and Nevis": { "country_ne":"Saint Kitts and Nevis", "pop_est":52715, "gdp_est":1427, "economy":"6. Developing region", "income_group":"2. High income: nonOECD", "continent":"North America", "region":"Americas"},
  "Saint Lucia": { "country_ne":"Saint Lucia", "pop_est":164994, "gdp_est":2083, "economy":"6. Developing region", "income_group":"3. Upper middle income", "continent":"North America", "region":"Americas"},
  "Saint Vincent and the Grenadines": { "country_ne":"Saint Vincent and the Grenadines", "pop_est":102089, "gdp_est":1241, "economy":"6. Developing region", "income_group":"3. Upper middle income", "continent":"North America", "region":"Americas"},
  "San Marino": { "country_ne":"San Marino", "pop_est":33537, "gdp_est":2023, "economy":"2. Developed region: nonG7", "income_group":"2. High income: nonOECD", "continent":"Europe", "region":"Europe"},
  "Sao Tome and Principe": { "country_ne":"Sao Tome and Principe", "pop_est":201025, "gdp_est":694, "economy":"7. Least developed region", "income_group":"4. Lower middle income", "continent":"Africa", "region":"Africa"},
  "Saudi Arabia": { "country_ne":"Saudi Arabia", "pop_est":28571770, "gdp_est":1731000, "economy":"2. Developed region: nonG7", "income_group":"2. High income: nonOECD", "continent":"Asia", "region":"Asia"},
  "Senegal": { "country_ne":"Senegal", "pop_est":14668522, "gdp_est":39720, "economy":"7. Least developed region", "income_group":"4. Lower middle income", "continent":"Africa", "region":"Africa"},
  "Serbia": { "country_ne":"Serbia", "pop_est":7111024, "gdp_est":101800, "economy":"6. Developing region", "income_group":"3. Upper middle income", "continent":"Europe", "region":"Europe"},
  "Seychelles": { "country_ne":"Seychelles", "pop_est":93920, "gdp_est":2608, "economy":"6. Developing region", "income_group":"3. Upper middle income", "continent":"Seven seas (open ocean)", "region":"Africa"},
  "Sierra Leone": { "country_ne":"Sierra Leone", "pop_est":6163195, "gdp_est":10640, "economy":"7. Least developed region", "income_group":"5. Low income", "continent":"Africa", "region":"Africa"},
  "Singapore": { "country_ne":"Singapore", "pop_est":5888926, "gdp_est":487900, "economy":"6. Developing region", "income_group":"2. High income: nonOECD", "continent":"Asia", "region":"Asia"},
  "Sint Maarten (Dutch part)": { "country_ne":"Sint Maarten", "pop_est":42083, "gdp_est":365.8, "economy":"6. Developing region", "income_group":"2. High income: nonOECD", "continent":"North America", "region":"Americas"},
  "Slovakia": { "country_ne":"Slovakia", "pop_est":5445829, "gdp_est":168800, "economy":"2. Developed region: nonG7", "income_group":"1. High income: OECD", "continent":"Europe", "region":"Europe"},
  "Slovenia": { "country_ne":"Slovenia", "pop_est":1972126, "gdp_est":68350, "economy":"2. Developed region: nonG7", "income_group":"1. High income: OECD", "continent":"Europe", "region":"Europe"},
  "Somalia": { "country_ne":"Somalia", "pop_est":7531386, "gdp_est":4719, "economy":"7. Least developed region", "income_group":"5. Low income", "continent":"Africa", "region":"Africa"},
  "South Africa": { "country_ne":"South Africa", "pop_est":54841552, "gdp_est":739100, "economy":"5. Emerging region: G20", "income_group":"3. Upper middle income", "continent":"Africa", "region":"Africa"},
  "South Korea": { "country_ne":"South Korea", "pop_est":51181299, "gdp_est":1929000, "economy":"4. Emerging region: MIKT", "income_group":"1. High income: OECD", "continent":"Asia", "region":"Asia"},
  "South Sudan": { "country_ne":"South Sudan", "pop_est":13026129, "gdp_est":20880, "economy":"7. Least developed region", "income_group":"5. Low income", "continent":"Africa", "region":"Africa"},
  "Spain": { "country_ne":"Spain", "pop_est":48958159, "gdp_est":1690000, "economy":"2. Developed region: nonG7", "income_group":"1. High income: OECD", "continent":"Europe", "region":"Europe"},
  "Sri Lanka": { "country_ne":"Sri Lanka", "pop_est":22409381, "gdp_est":236700, "economy":"6. Developing region", "income_group":"4. Lower middle income", "continent":"Asia", "region":"Asia"},
  "Sudan": { "country_ne":"Sudan", "pop_est":37345935, "gdp_est":176300, "economy":"6. Developing region", "income_group":"4. Lower middle income", "continent":"Africa", "region":"Africa"},
  "Suriname": { "country_ne":"Suriname", "pop_est":591919, "gdp_est":8547, "economy":"6. Developing region", "income_group":"3. Upper middle income", "continent":"South America", "region":"Americas"},
  "Swaziland": { "country_ne":"", "pop_est":0, "gdp_est":0, "economy":"", "income_group":"", "continent":"", "region":""},
  "Sweden": { "country_ne":"Sweden", "pop_est":9960487, "gdp_est":498100, "economy":"2. Developed region: nonG7", "income_group":"1. High income: OECD", "continent":"Europe", "region":"Europe"},
  "Switzerland": { "country_ne":"Switzerland", "pop_est":8236303, "gdp_est":496300, "economy":"2. Developed region: nonG7", "income_group":"1. High income: OECD", "continent":"Europe", "region":"Europe"},
  "Syria": { "country_ne":"Syria", "pop_est":18028549, "gdp_est":50280, "economy":"6. Developing region", "income_group":"4. Lower middle income", "continent":"Asia", "region":"Asia"},
  "Taiwan": { "country_ne":"Taiwan", "pop_est":23508428, "gdp_est":1127000, "economy":"2. Developed region: nonG7", "income_group":"2. High income: nonOECD", "continent":"Asia", "region":"Asia"},
  "Tajikistan": { "country_ne":"Tajikistan", "pop_est":8468555, "gdp_est":25810, "economy":"6. Developing region", "income_group":"5. Low income", "continent":"Asia", "region":"Asia"},
  "Tanzania": { "country_ne":"Tanzania", "pop_est":53950935, "gdp_est":150600, "economy":"7. Least developed region", "income_group":"5. Low income", "continent":"Africa", "region":"Africa"},
  "Thailand": { "country_ne":"Thailand", "pop_est":68414135, "gdp_est":1161000, "economy":"5. Emerging region: G20", "income_group":"3. Upper middle income", "continent":"Asia", "region":"Asia"},
  "Timor": { "country_ne":"East Timor", "pop_est":1291358, "gdp_est":4975, "economy":"7. Least developed region", "income_group":"4. Lower middle income", "continent":"Asia", "region":"Asia"},
  "Togo": { "country_ne":"Togo", "pop_est":7965055, "gdp_est":11610, "economy":"7. Least developed region", "income_group":"5. Low income", "continent":"Africa", "region":"Africa"},
  "Trinidad and Tobago": { "country_ne":"Trinidad and Tobago", "pop_est":1218208, "gdp_est":43570, "economy":"6. Developing region", "income_group":"2. High income: nonOECD", "continent":"North America", "region":"Americas"},
  "Tunisia": { "country_ne":"Tunisia", "pop_est":11403800, "gdp_est":130800, "economy":"6. Developing region", "income_group":"3. Upper middle income", "continent":"Africa", "region":"Africa"},
  "Turkey": { "country_ne":"Turkey", "pop_est":80845215, "gdp_est":1670000, "economy":"4. Emerging region: MIKT", "income_group":"3. Upper middle income", "continent":"Asia", "region":"Asia"},
  "Turks and Caicos Islands": { "country_ne":"Turks and Caicos Islands", "pop_est":52570, "gdp_est":632, "economy":"6. Developing region", "income_group":"2. High income: nonOECD", "continent":"North America", "region":"Americas"},
  "Uganda": { "country_ne":"Uganda", "pop_est":39570125, "gdp_est":84930, "economy":"7. Least developed region", "income_group":"5. Low income", "continent":"Africa", "region":"Africa"},
  "Ukraine": { "country_ne":"Ukraine", "pop_est":44033874, "gdp_est":352600, "economy":"6. Developing region", "income_group":"4. Lower middle income", "continent":"Europe", "region":"Europe"},
  "United Arab Emirates": { "country_ne":"United Arab Emirates", "pop_est":6072475, "gdp_est":667200, "economy":"6. Developing region", "income_group":"2. High income: nonOECD", "continent":"Asia", "region":"Asia"},
  "United Kingdom": { "country_ne":"United Kingdom", "pop_est":64769452, "gdp_est":2788000, "economy":"1. Developed region: G7", "income_group":"1. High income: OECD", "continent":"Europe", "region":"Europe"},
  "United States": { "country_ne":"United States", "pop_est":326625791, "gdp_est":18560000, "economy":"1. Developed region: G7", "income_group":"1. High income: OECD", "continent":"North America", "region":"Americas"},
  "United States Virgin Islands": { "country_ne":"United States Virgin Islands", "pop_est":107268, "gdp_est":3792, "economy":"6. Developing region", "income_group":"2. High income: nonOECD", "continent":"North America", "region":"Americas"},
  "Uruguay": { "country_ne":"Uruguay", "pop_est":3360148, "gdp_est":73250, "economy":"5. Emerging region: G20", "income_group":"3. Upper middle income", "continent":"South America", "region":"Americas"},
  "Uzbekistan": { "country_ne":"Uzbekistan", "pop_est":29748859, "gdp_est":202300, "economy":"6. Developing region", "income_group":"4. Lower middle income", "continent":"Asia", "region":"Asia"},
  "Vatican": { "country_ne":"Vatican", "pop_est":1000, "gdp_est":0, "economy":"2. Developed region: nonG7", "income_group":"2. High income: nonOECD", "continent":"Europe", "region":"Europe"},
  "Venezuela": { "country_ne":"Venezuela", "pop_est":31304016, "gdp_est":468600, "economy":"5. Emerging region: G20", "income_group":"3. Upper middle income", "continent":"South America", "region":"Americas"},
  "Vietnam": { "country_ne":"Vietnam", "pop_est":96160163, "gdp_est":594900, "economy":"5. Emerging region: G20", "income_group":"4. Lower middle income", "continent":"Asia", "region":"Asia"},
  "Western Sahara": { "country_ne":"Western Sahara", "pop_est":603253, "gdp_est":906.5, "economy":"7. Least developed region", "income_group":"5. Low income", "continent":"Africa", "region":"Africa"},
  "Yemen": { "country_ne":"Yemen", "pop_est":28036829, "gdp_est":73450, "economy":"7. Least developed region", "income_group":"4. Lower middle income", "continent":"Asia", "region":"Asia"},
  "Zambia": { "country_ne":"Zambia", "pop_est":15972000, "gdp_est":65170, "economy":"7. Least developed region", "income_group":"4. Lower middle income", "continent":"Africa", "region":"Africa"},
  "Zimbabwe": { "country_ne":"Zimbabwe", "pop_est":13805084, "gdp_est":28330, "economy":"5. Emerging region: G20", "income_group":"5. Low income", "continent":"Africa", "region":"Africa"}
}